gspec/__init__.py
gspec/mediso.py
gspec/plotter.py
gspec/spectrum.py
gspec-1.0.1.dist-info/LICENSE
gspec-1.0.1.dist-info/METADATA
gspec-1.0.1.dist-info/WHEEL
gspec-1.0.1.dist-info/top_level.txt
gspec-1.0.1.dist-info/RECORD
