Metadata-Version: 2.1
Name: gspec
Version: 1.0.1
Summary: Gamma spectroscopy tools
Home-page: https://github.com/cwand/gspec
Author: Chris Walther Andersen
Author-email: christian.walther.andersen@rsyd.dk
License: UNKNOWN
Project-URL: Bug Tracker, https://github.com/cwand/gspec/issues
Platform: UNKNOWN
Classifier: Programming Language :: Python :: 3
Classifier: License :: OSI Approved :: MIT License
Classifier: Operating System :: OS Independent
Requires-Python: >=3.8
License-File: LICENSE
Requires-Dist: numpy (>=1.21)
Requires-Dist: scipy (>=1.7)
Requires-Dist: matplotlib (>=3.3)
Requires-Dist: pydicom (>=2.2)
Provides-Extra: testing
Requires-Dist: pytest (>=6.0) ; extra == 'testing'
Requires-Dist: pytest-cov (>=2.0) ; extra == 'testing'
Requires-Dist: mypy (>=0.910) ; extra == 'testing'
Requires-Dist: flake8 (>=3.9) ; extra == 'testing'
Requires-Dist: tox (>=3.24) ; extra == 'testing'
